mypyliex/classes/printer.py
mypyliex/classes/system.py
mypyliex/classes/user.py
mypyliex/tools/next_tool_name/constants.py
mypyliex/tools/next_tool_name/next_tool_name.py
mypyliex/tools/other_tool_name/constants.py
mypyliex/tools/other_tool_name/other_tool_name.py
mypyliex/tools/printer/constants.py
mypyliex/tools/printer/printer.py
mypyliex-22.6.8.dist-info/METADATA
mypyliex-22.6.8.dist-info/WHEEL
mypyliex-22.6.8.dist-info/entry_points.txt
mypyliex-22.6.8.dist-info/top_level.txt
mypyliex-22.6.8.dist-info/RECORD
